LICENSE
MANIFEST.in
README.rst
setup.py
cash_register/__init__.py
cash_register/exceptions.py
cash_register/commands/__init__.py
cash_register/commands/base.py
cash_register/commands/sell.py
cash_register/models/__init__.py
cash_register/models/base.py
cash_register/models/xditron.py
python_cash_register.egg-info/PKG-INFO
python_cash_register.egg-info/SOURCES.txt
python_cash_register.egg-info/dependency_links.txt
python_cash_register.egg-info/not-zip-safe
python_cash_register.egg-info/top_level.txt
tests/__init__.py
tests/test_commands.py
tests/test_exceptions.py
tests/test_models.py
tests/test_models_xditron.py
tests/test_sell.py