Metadata-Version: 1.1
Name: python-cash-register
Version: 0.1.1
Summary: A set of Python bindings to control cash registers
Home-page: https://github.com/palazzem/python-cash-register
Author: Emanuele Palazzetti
Author-email: hello@palazzetti.me
License: BSD
Keywords: cash register
Platform: UNKNOWN
Classifier: Development Status :: 4 - Beta
Classifier: Environment :: Web Environment
Classifier: License :: OSI Approved :: BSD License
Classifier: Operating System :: OS Independent
Classifier: Programming Language :: Python :: 2.7
Classifier: Programming Language :: Python :: 3.3
Classifier: Programming Language :: Python :: 3.4
Classifier: Programming Language :: Python :: 3.5
Classifier: Topic :: Software Development :: Libraries :: Python Modules
